{"data":[{"quest_id":25,"title":"ニケのやる気と眠気","is_restricted":false,"is_r18":false,"harem_episode_info":{"episode_id":"25_harem-character","heroine_is_aroused":false,"cleared_bonus_type":"none","is_story_of_encounter":true,"heroines":[{"heroine_type":"character","heroine_id":26,"name":"ニケ"}],"condition_to_unlock":{"heroine_name":"ニケ","episode_title":"","level":1},"chapters":[{"a_chapter_id":"100260","chapter_id":"25_harem-character","title":"第1話","is_cleared":true,"is_opened":true}]},"reward_info":{"reward_type":"item","item_id":1},"a_quest_id":"100260","is_new":false,"is_cleared":true,"is_opened":true,"has_area_boss":false,"description":"相変わらず寝坊してしまうニケ。\nアリサはニケの強さに疑問を抱く。\n強い、と主張するニケだがはたして？","type":"harem-character","quest_ap":0},{"quest_id":26,"title":"バニーガールのロマン","is_restricted":false,"is_r18":true,"harem_episode_info":{"episode_id":"26_harem-character","heroine_is_aroused":false,"cleared_bonus_type":"acquire_ability","is_story_of_encounter":false,"heroines":[{"heroine_type":"character","heroine_id":26,"name":"ニケ"}],"condition_to_unlock":{"heroine_name":"ニケ","episode_title":"ニケのやる気と眠気","level":35},"chapters":[{"a_chapter_id":"100261","chapter_id":"26_harem-character","title":"第1話","is_cleared":false,"is_opened":true}]},"a_quest_id":"100261","is_new":true,"is_cleared":false,"is_opened":true,"has_area_boss":false,"description":"宿屋の女の子に頼まれ、\n快く仕事を手伝うニケと主人公。\nそんなニケに支給された驚きの制服とは？","type":"harem-character","quest_ap":0},{"quest_id":27,"title":"門番プレイ！","is_restricted":false,"is_r18":true,"harem_episode_info":{"episode_id":"27_harem-character","heroine_is_aroused":false,"cleared_bonus_type":"none","is_story_of_encounter":false,"heroines":[{"heroine_type":"character","heroine_id":26,"name":"ニケ"}],"condition_to_unlock":{"heroine_name":"ニケ","episode_title":"バニーガールのロマン","level":55},"chapters":[{"a_chapter_id":"100262","chapter_id":"27_harem-character","title":"第1話","is_cleared":false,"is_opened":true}]},"reward_info":{"reward_type":"item","item_id":1},"a_quest_id":"100262","is_new":true,"is_cleared":false,"is_opened":true,"has_area_boss":false,"description":"ひょんなことから門番をする事になった\n主人公とニケ。しかし、平和な時間が流れ、\n暇を持て余した二人は門番ごっこに興じる。","type":"harem-character","quest_ap":0}],"max_record_count":3}