{"data":[{"quest_id":9704,"title":"攻める楯","is_restricted":false,"is_r18":false,"harem_episode_info":{"episode_id":"9704_harem-character","heroine_is_aroused":false,"cleared_bonus_type":"none","is_story_of_encounter":true,"heroines":[{"heroine_type":"character","heroine_id":6177,"name":"[疾風打盾]ランダ"}],"condition_to_unlock":{"heroine_name":"[疾風打盾]ランダ","episode_title":"","level":1},"chapters":[{"a_chapter_id":"161771","chapter_id":"9704_harem-character","title":"第1話","is_cleared":true,"is_opened":true}]},"reward_info":{"reward_type":"item","item_id":1},"a_quest_id":"161771","is_new":false,"is_cleared":true,"is_opened":true,"has_area_boss":false,"description":"打撃武器として使える楯を手に、仲間を\n守ろうと頑張るランダ。だが気持ちが\n空回りして足を引っ張ってしまう……。","type":"harem-character","quest_ap":0},{"quest_id":9705,"title":"セクシーなライン","is_restricted":false,"is_r18":true,"harem_episode_info":{"episode_id":"9705_harem-character","heroine_is_aroused":false,"cleared_bonus_type":"acquire_ability","is_story_of_encounter":false,"heroines":[{"heroine_type":"character","heroine_id":6177,"name":"[疾風打盾]ランダ"}],"condition_to_unlock":{"heroine_name":"[疾風打盾]ランダ","episode_title":"攻める楯","level":45},"chapters":[{"a_chapter_id":"161772","chapter_id":"9705_harem-character","title":"第1話","is_cleared":false,"is_opened":true}]},"a_quest_id":"161772","is_new":true,"is_cleared":false,"is_opened":true,"has_area_boss":false,"description":"訓練で汗をかき、スーツを肌に張り付けた\nランダ。それにより強調された彼女の\n美しいボディラインを見た主人公は……。","type":"harem-character","quest_ap":0},{"quest_id":9706,"title":"路地裏の情事","is_restricted":false,"is_r18":true,"harem_episode_info":{"episode_id":"9706_harem-character","heroine_is_aroused":false,"cleared_bonus_type":"none","is_story_of_encounter":false,"heroines":[{"heroine_type":"character","heroine_id":6177,"name":"[疾風打盾]ランダ"}],"condition_to_unlock":{"heroine_name":"[疾風打盾]ランダ","episode_title":"セクシーなライン","level":65},"chapters":[{"a_chapter_id":"161773","chapter_id":"9706_harem-character","title":"第1話","is_cleared":false,"is_opened":true}]},"reward_info":{"reward_type":"item","item_id":1},"a_quest_id":"161773","is_new":true,"is_cleared":false,"is_opened":true,"has_area_boss":false,"description":"ランダのおかげで気持ちよくなれた\n主人公。だが一方でランダはどこか\nよそよそしい様子を見せる……。","type":"harem-character","quest_ap":0}],"max_record_count":3}