{"data":[{"quest_id":4809,"title":"自分の魅力","is_restricted":false,"is_r18":false,"harem_episode_info":{"episode_id":"4809_harem-character","heroine_is_aroused":false,"cleared_bonus_type":"none","is_story_of_encounter":true,"heroines":[{"heroine_type":"character","heroine_id":7065,"name":"[魅惑の魔女]キルケー"}],"condition_to_unlock":{"heroine_name":"[魅惑の魔女]キルケー","episode_title":"","level":1},"chapters":[{"a_chapter_id":"170650","chapter_id":"4809_harem-character","title":"第1話","is_cleared":true,"is_opened":true}]},"reward_info":{"reward_type":"item","item_id":1},"a_quest_id":"170650","is_new":false,"is_cleared":true,"is_opened":true,"has_area_boss":false,"description":"アリサの指摘で、誘惑魔法に頼りすぎている\nことに気づくキルケー。すぐさま彼女は己の\n魅力で、主人公を誘惑しようとするが――","type":"harem-character","quest_ap":0},{"quest_id":4810,"title":"誘惑魔法の暴発","is_restricted":false,"is_r18":true,"harem_episode_info":{"episode_id":"4810_harem-character","heroine_is_aroused":false,"cleared_bonus_type":"acquire_ability","is_story_of_encounter":false,"heroines":[{"heroine_type":"character","heroine_id":7065,"name":"[魅惑の魔女]キルケー"}],"condition_to_unlock":{"heroine_name":"[魅惑の魔女]キルケー","episode_title":"自分の魅力","level":35},"chapters":[{"a_chapter_id":"170651","chapter_id":"4810_harem-character","title":"第1話","is_cleared":false,"is_opened":true}]},"a_quest_id":"170651","is_new":true,"is_cleared":false,"is_opened":true,"has_area_boss":false,"description":"威力を増した誘惑魔法で、主人公を虜に\nしようと画策するキルケー。しかし、魔力を\n込めすぎたため制御することができず――","type":"harem-character","quest_ap":0}],"max_record_count":2}