{"data":[{"quest_id":437,"title":"愛に揺らぐ男性恐怖症","is_restricted":false,"is_r18":false,"harem_episode_info":{"episode_id":"437_harem-character","heroine_is_aroused":false,"cleared_bonus_type":"none","is_story_of_encounter":true,"heroines":[{"heroine_type":"character","heroine_id":7030,"name":"ダプネー"}],"condition_to_unlock":{"heroine_name":"ダプネー","episode_title":"","level":1},"chapters":[{"a_chapter_id":"170300","chapter_id":"437_harem-character","title":"第1話","is_cleared":true,"is_opened":true}]},"reward_info":{"reward_type":"item","item_id":1},"a_quest_id":"170300","is_new":false,"is_cleared":true,"is_opened":true,"has_area_boss":false,"description":"主人公達が休憩を求めて木陰に入ると、\n突如木が神姫に変貌する。現れた神姫は\n主人公に一目惚れするも、男性恐怖症で─","type":"harem-character","quest_ap":0},{"quest_id":438,"title":"男が怖いなら……","is_restricted":false,"is_r18":true,"harem_episode_info":{"episode_id":"438_harem-character","heroine_is_aroused":false,"cleared_bonus_type":"acquire_ability","is_story_of_encounter":false,"heroines":[{"heroine_type":"character","heroine_id":7030,"name":"ダプネー"}],"condition_to_unlock":{"heroine_name":"ダプネー","episode_title":"愛に揺らぐ男性恐怖症","level":25},"chapters":[{"a_chapter_id":"170301","chapter_id":"438_harem-character","title":"第1話","is_cleared":false,"is_opened":true}]},"a_quest_id":"170301","is_new":true,"is_cleared":false,"is_opened":true,"has_area_boss":false,"description":"ショック療法を企て、夜中に主人公を訪ねる\nダプネー。が、やはり怖気付いたダプネーは\nメイド服を主人公に着てもらう事に。","type":"harem-character","quest_ap":0}],"max_record_count":2}