{"data":[{"quest_id":4501,"title":"いきすぎた忠誠心","is_restricted":false,"is_r18":false,"harem_episode_info":{"episode_id":"4501_harem-character","heroine_is_aroused":false,"cleared_bonus_type":"none","is_story_of_encounter":true,"heroines":[{"heroine_type":"character","heroine_id":5095,"name":"[黒焔のメイド]アモン"}],"condition_to_unlock":{"heroine_name":"[黒焔のメイド]アモン","episode_title":"","level":1},"chapters":[{"a_chapter_id":"150950","chapter_id":"4501_harem-character","title":"第1話","is_cleared":true,"is_opened":true}]},"reward_info":{"reward_type":"item","item_id":1},"a_quest_id":"150950","is_new":false,"is_cleared":true,"is_opened":true,"has_area_boss":false,"description":"アモンに辟易し、逃げ出すディアボロス。\nいなくなった主を必死に探すアモンは、\nディアボロスがとある廃屋に入ったと聞く。","type":"harem-character","quest_ap":0},{"quest_id":4502,"title":"毒薬変じて薬となる？","is_restricted":false,"is_r18":true,"harem_episode_info":{"episode_id":"4502_harem-character","heroine_is_aroused":false,"cleared_bonus_type":"acquire_ability","is_story_of_encounter":false,"heroines":[{"heroine_type":"character","heroine_id":5095,"name":"[黒焔のメイド]アモン"}],"condition_to_unlock":{"heroine_name":"[黒焔のメイド]アモン","episode_title":"いきすぎた忠誠心","level":35},"chapters":[{"a_chapter_id":"150951","chapter_id":"4502_harem-character","title":"第1話","is_cleared":false,"is_opened":true}]},"a_quest_id":"150951","is_new":true,"is_cleared":false,"is_opened":true,"has_area_boss":false,"description":"ハーブを採取しようと森へ向かうアモン達。\n途中、主人公が誤って毒草を食べてしまう。\n運良く毒草を吐き出した主人公だが……。","type":"harem-character","quest_ap":0},{"quest_id":4503,"title":"終わりなき戦い","is_restricted":false,"is_r18":true,"harem_episode_info":{"episode_id":"4503_harem-character","heroine_is_aroused":false,"cleared_bonus_type":"none","is_story_of_encounter":false,"heroines":[{"heroine_type":"character","heroine_id":5095,"name":"[黒焔のメイド]アモン"}],"condition_to_unlock":{"heroine_name":"[黒焔のメイド]アモン","episode_title":"毒薬変じて薬となる？","level":55},"chapters":[{"a_chapter_id":"150952","chapter_id":"4503_harem-character","title":"第1話","is_cleared":false,"is_opened":true}]},"reward_info":{"reward_type":"item","item_id":1},"a_quest_id":"150952","is_new":true,"is_cleared":false,"is_opened":true,"has_area_boss":false,"description":"主人公を何度も射精させるアモン。\nしかし、一向に鎮まらないペニスを見て\n彼女は最後の手段を使うことに――。","type":"harem-character","quest_ap":0}],"max_record_count":3}