{"data":[{"quest_id":5409,"title":"財宝より大切なもの","is_restricted":false,"is_r18":false,"harem_episode_info":{"episode_id":"5409_harem-character","heroine_is_aroused":false,"cleared_bonus_type":"none","is_story_of_encounter":true,"heroines":[{"heroine_type":"character","heroine_id":7071,"name":"[海浜の雷運]ダジボーグ"}],"condition_to_unlock":{"heroine_name":"[海浜の雷運]ダジボーグ","episode_title":"","level":1},"chapters":[{"a_chapter_id":"170710","chapter_id":"5409_harem-character","title":"第1話","is_cleared":true,"is_opened":true}]},"reward_info":{"reward_type":"item","item_id":1},"a_quest_id":"170710","is_new":false,"is_cleared":true,"is_opened":true,"has_area_boss":false,"description":"バカンスを満喫していたダジボーグは、偶然\n砂浜で宝の地図を発見する。財宝を求め、\n主人公と洞窟に出向いた彼女だったが――","type":"harem-character","quest_ap":0},{"quest_id":5410,"title":"楽しいバカンスで……","is_restricted":false,"is_r18":true,"harem_episode_info":{"episode_id":"5410_harem-character","heroine_is_aroused":false,"cleared_bonus_type":"acquire_ability","is_story_of_encounter":false,"heroines":[{"heroine_type":"character","heroine_id":7071,"name":"[海浜の雷運]ダジボーグ"}],"condition_to_unlock":{"heroine_name":"[海浜の雷運]ダジボーグ","episode_title":"財宝より大切なもの","level":35},"chapters":[{"a_chapter_id":"170711","chapter_id":"5410_harem-character","title":"第1話","is_cleared":false,"is_opened":true}]},"a_quest_id":"170711","is_new":true,"is_cleared":false,"is_opened":true,"has_area_boss":false,"description":"持ち前のドジで主人公を巻き込み、砂浜に\n倒れこむダジボーグ。これ幸いと体を密着\nさせた彼女は。主人公を誘惑し始め――","type":"harem-character","quest_ap":0}],"max_record_count":2}