{"data":[{"quest_id":7113,"title":"侘寂の意味","is_restricted":false,"is_r18":false,"harem_episode_info":{"episode_id":"7113_harem-character","heroine_is_aroused":false,"cleared_bonus_type":"none","is_story_of_encounter":true,"heroines":[{"heroine_type":"character","heroine_id":7085,"name":"[侘寂の雷歌]オルフェウス"}],"condition_to_unlock":{"heroine_name":"[侘寂の雷歌]オルフェウス","episode_title":"","level":1},"chapters":[{"a_chapter_id":"170850","chapter_id":"7113_harem-character","title":"第1話","is_cleared":true,"is_opened":true}]},"reward_info":{"reward_type":"item","item_id":1},"a_quest_id":"170850","is_new":false,"is_cleared":true,"is_opened":true,"has_area_boss":false,"description":"新たな自分をファンに見せる為、演歌に\n挑戦しようとするオルフェウス。和の心を\n理解する為に、彼女の厳しい修行が始まる！","type":"harem-character","quest_ap":0},{"quest_id":7114,"title":"芸者遊び？","is_restricted":false,"is_r18":true,"harem_episode_info":{"episode_id":"7114_harem-character","heroine_is_aroused":false,"cleared_bonus_type":"acquire_ability","is_story_of_encounter":false,"heroines":[{"heroine_type":"character","heroine_id":7085,"name":"[侘寂の雷歌]オルフェウス"}],"condition_to_unlock":{"heroine_name":"[侘寂の雷歌]オルフェウス","episode_title":"侘寂の意味","level":35},"chapters":[{"a_chapter_id":"170851","chapter_id":"7114_harem-character","title":"第1話","is_cleared":false,"is_opened":true}]},"a_quest_id":"170851","is_new":true,"is_cleared":false,"is_opened":true,"has_area_boss":false,"description":"和の心を学んでいたオルフェウスは、芸者\n遊びに興味を持つ。内容を知らない彼女は、\n無邪気な様子で、主人公を誘うのだが――","type":"harem-character","quest_ap":0}],"max_record_count":2}