{"data":[{"quest_id":5801,"title":"勇気の剣","is_restricted":false,"is_r18":false,"harem_episode_info":{"episode_id":"5801_harem-character","heroine_is_aroused":false,"cleared_bonus_type":"none","is_story_of_encounter":true,"heroines":[{"heroine_type":"character","heroine_id":5113,"name":"イリス"}],"condition_to_unlock":{"heroine_name":"イリス","episode_title":"","level":1},"chapters":[{"a_chapter_id":"151130","chapter_id":"5801_harem-character","title":"第1話","is_cleared":true,"is_opened":true}]},"reward_info":{"reward_type":"item","item_id":1},"a_quest_id":"151130","is_new":false,"is_cleared":true,"is_opened":true,"has_area_boss":false,"description":"封印装置ごと競売に出されたイリスを救った\n主人公一行。しかしイリスに執心の落札者が\n機械兵を差し向け、一行に襲い掛かる――","type":"harem-character","quest_ap":0},{"quest_id":5802,"title":"シチューハプニング","is_restricted":false,"is_r18":true,"harem_episode_info":{"episode_id":"5802_harem-character","heroine_is_aroused":false,"cleared_bonus_type":"acquire_ability","is_story_of_encounter":false,"heroines":[{"heroine_type":"character","heroine_id":5113,"name":"イリス"}],"condition_to_unlock":{"heroine_name":"イリス","episode_title":"勇気の剣","level":35},"chapters":[{"a_chapter_id":"151131","chapter_id":"5802_harem-character","title":"第1話","is_cleared":false,"is_opened":true}]},"a_quest_id":"151131","is_new":true,"is_cleared":false,"is_opened":true,"has_area_boss":false,"description":"零したシチューで服を汚すイリスと主人公。\n洗濯のため下着姿になったイリスは、主人公\nもと言いながら彼のズボンを脱がせ始め――","type":"harem-character","quest_ap":0},{"quest_id":5803,"title":"アツアツを冷ますには","is_restricted":false,"is_r18":true,"harem_episode_info":{"episode_id":"5803_harem-character","heroine_is_aroused":false,"cleared_bonus_type":"none","is_story_of_encounter":false,"heroines":[{"heroine_type":"character","heroine_id":5113,"name":"イリス"}],"condition_to_unlock":{"heroine_name":"イリス","episode_title":"シチューハプニング","level":55},"chapters":[{"a_chapter_id":"151132","chapter_id":"5803_harem-character","title":"第1話","is_cleared":false,"is_opened":true}]},"reward_info":{"reward_type":"item","item_id":1},"a_quest_id":"151132","is_new":true,"is_cleared":false,"is_opened":true,"has_area_boss":false,"description":"行為を思い出し恥じるイリス。そんな彼女に\n興奮した主人公のペニスは再度勃起。戸惑う\nイリスに主人公が告げた、ある方法とは……","type":"harem-character","quest_ap":0}],"max_record_count":3}