{"data":[{"quest_id":10004,"title":"鼓舞する奮迅槍","is_restricted":false,"is_r18":false,"harem_episode_info":{"episode_id":"10004_harem-character","heroine_is_aroused":false,"cleared_bonus_type":"none","is_story_of_encounter":true,"heroines":[{"heroine_type":"character","heroine_id":6181,"name":"[奮迅の水槍]ミフル"}],"condition_to_unlock":{"heroine_name":"[奮迅の水槍]ミフル","episode_title":"","level":1},"chapters":[{"a_chapter_id":"161811","chapter_id":"10004_harem-character","title":"第1話","is_cleared":true,"is_opened":true}]},"reward_info":{"reward_type":"item","item_id":1},"a_quest_id":"161811","is_new":false,"is_cleared":true,"is_opened":true,"has_area_boss":false,"description":"魔物に襲われた街へ救援に来た主人公達。\n終わりの見えない戦いに皆戦意を失う中、\nミフルは獅子奮迅の活躍を見せる。","type":"harem-character","quest_ap":0},{"quest_id":10005,"title":"信頼しあうための準備","is_restricted":false,"is_r18":true,"harem_episode_info":{"episode_id":"10005_harem-character","heroine_is_aroused":false,"cleared_bonus_type":"acquire_ability","is_story_of_encounter":false,"heroines":[{"heroine_type":"character","heroine_id":6181,"name":"[奮迅の水槍]ミフル"}],"condition_to_unlock":{"heroine_name":"[奮迅の水槍]ミフル","episode_title":"鼓舞する奮迅槍","level":45},"chapters":[{"a_chapter_id":"161812","chapter_id":"10005_harem-character","title":"第1話","is_cleared":false,"is_opened":true}]},"a_quest_id":"161812","is_new":true,"is_cleared":false,"is_opened":true,"has_area_boss":false,"description":"部隊を作るため信頼関係を築く方法を学ぶ\nミフル。手始めに主人公と信頼を築くため\n彼女はある方法を選び準備を進める。","type":"harem-character","quest_ap":0},{"quest_id":10006,"title":"強固な繋がり","is_restricted":false,"is_r18":true,"harem_episode_info":{"episode_id":"10006_harem-character","heroine_is_aroused":false,"cleared_bonus_type":"none","is_story_of_encounter":false,"heroines":[{"heroine_type":"character","heroine_id":6181,"name":"[奮迅の水槍]ミフル"}],"condition_to_unlock":{"heroine_name":"[奮迅の水槍]ミフル","episode_title":"信頼しあうための準備","level":65},"chapters":[{"a_chapter_id":"161813","chapter_id":"10006_harem-character","title":"第1話","is_cleared":false,"is_opened":true}]},"reward_info":{"reward_type":"item","item_id":1},"a_quest_id":"161813","is_new":true,"is_cleared":false,"is_opened":true,"has_area_boss":false,"description":"主人公を呼び出したミフルはセックスしたい\nと急に言い出す。だがすぐに唐突だったと\n謝り、事情を説明し始める。","type":"harem-character","quest_ap":0}],"max_record_count":3}