{"data":[{"quest_id":8007,"title":"噂のあーちゃん先生","is_restricted":false,"is_r18":false,"harem_episode_info":{"episode_id":"8007_harem-character","heroine_is_aroused":false,"cleared_bonus_type":"none","is_story_of_encounter":true,"heroines":[{"heroine_type":"character","heroine_id":7094,"name":"アリスタイオス"}],"condition_to_unlock":{"heroine_name":"アリスタイオス","episode_title":"","level":1},"chapters":[{"a_chapter_id":"170941","chapter_id":"8007_harem-character","title":"第1話","is_cleared":true,"is_opened":true}]},"reward_info":{"reward_type":"item","item_id":1},"a_quest_id":"170941","is_new":false,"is_cleared":true,"is_opened":true,"has_area_boss":false,"description":"ある神姫が大きくしたと噂の村を訪れた\n主人公達。そこは先生と呼ばれる神姫が\n鍛えた屈強な兵が守る、立派な村だった。","type":"harem-character","quest_ap":0},{"quest_id":8008,"title":"正しいセックス講座","is_restricted":false,"is_r18":true,"harem_episode_info":{"episode_id":"8008_harem-character","heroine_is_aroused":false,"cleared_bonus_type":"acquire_ability","is_story_of_encounter":false,"heroines":[{"heroine_type":"character","heroine_id":7094,"name":"アリスタイオス"}],"condition_to_unlock":{"heroine_name":"アリスタイオス","episode_title":"噂のあーちゃん先生","level":45},"chapters":[{"a_chapter_id":"170942","chapter_id":"8008_harem-character","title":"第1話","is_cleared":false,"is_opened":true}]},"a_quest_id":"170942","is_new":true,"is_cleared":false,"is_opened":true,"has_area_boss":false,"description":"身勝手な性行為をしていると主人公を叱る\nアリスタイオス。性行為とはかくあるべきと\n彼女の話を聞いているうちに主人公は……。","type":"harem-character","quest_ap":0}],"max_record_count":2}