{"data":[{"quest_id":6901,"title":"頑張る子への贈り物","is_restricted":false,"is_r18":false,"harem_episode_info":{"episode_id":"6901_harem-summon","heroine_is_aroused":false,"cleared_bonus_type":"none","is_story_of_encounter":true,"heroines":[{"heroine_type":"summon","heroine_id":6078,"name":"[祝宴の聖音]ストラス"}],"condition_to_unlock":{"heroine_name":"[祝宴の聖音]ストラス","episode_title":"","level":1},"chapters":[{"a_chapter_id":"260781","chapter_id":"6901_harem-summon","title":"第1話","is_cleared":true,"is_opened":true}]},"reward_info":{"reward_type":"item","item_id":1},"a_quest_id":"260781","is_new":false,"is_cleared":true,"is_opened":true,"has_area_boss":false,"description":"クリスマスが終わり、オルガンを返すことに\nなったストラス。悲しそうな彼女を見かけた\nプリンシパリティは、ある計画を立てる。","type":"harem-summon","quest_ap":0},{"quest_id":6902,"title":"褒められて伸びる子","is_restricted":false,"is_r18":true,"harem_episode_info":{"episode_id":"6902_harem-summon","heroine_is_aroused":false,"cleared_bonus_type":"acquire_ability","is_story_of_encounter":false,"heroines":[{"heroine_type":"summon","heroine_id":6078,"name":"[祝宴の聖音]ストラス"}],"condition_to_unlock":{"heroine_name":"[祝宴の聖音]ストラス","episode_title":"頑張る子への贈り物","level":45},"chapters":[{"a_chapter_id":"260782","chapter_id":"6902_harem-summon","title":"第1話","is_cleared":false,"is_opened":true}]},"a_quest_id":"260782","is_new":true,"is_cleared":false,"is_opened":true,"has_area_boss":false,"description":"ジュースと間違えて、ワインを口にした\nストラス。ふとした拍子に身体が触れると\n酔った彼女は主人公に言い寄り始め――。","type":"harem-summon","quest_ap":0}],"max_record_count":2}