{"data":[{"quest_id":6204,"title":"因縁の対決","is_restricted":false,"is_r18":false,"harem_episode_info":{"episode_id":"6204_harem-character","heroine_is_aroused":true,"cleared_bonus_type":"none","is_story_of_encounter":true,"heroines":[{"heroine_type":"character","heroine_id":5119,"name":"アザゼル[神化覚醒]"}],"condition_to_unlock":{"heroine_name":"アザゼル[神化覚醒]","episode_title":"","level":1},"chapters":[{"a_chapter_id":"151190","chapter_id":"6204_harem-character","title":"第1話","is_cleared":true,"is_opened":true}]},"reward_info":{"reward_type":"item","item_id":1},"a_quest_id":"151190","is_new":false,"is_cleared":true,"is_opened":true,"has_area_boss":false,"description":"因縁の神姫と戦闘を繰り広げるアザゼル。\n神姫は人間の可能性を奪い、挙げ句未来を\n消し去る存在だと叫ぶアザゼルだが……。","type":"harem-character","quest_ap":0},{"quest_id":6205,"title":"人の持つ可能性","is_restricted":false,"is_r18":true,"harem_episode_info":{"episode_id":"6205_harem-character","heroine_is_aroused":true,"cleared_bonus_type":"acquire_ability","is_story_of_encounter":false,"heroines":[{"heroine_type":"character","heroine_id":5119,"name":"アザゼル[神化覚醒]"}],"condition_to_unlock":{"heroine_name":"アザゼル[神化覚醒]","episode_title":"因縁の対決","level":35},"chapters":[{"a_chapter_id":"151191","chapter_id":"6205_harem-character","title":"第1話","is_cleared":false,"is_opened":true}]},"a_quest_id":"151191","is_new":true,"is_cleared":false,"is_opened":true,"has_area_boss":false,"description":"依頼を頑張ってくれたアザゼルに差し入れ\nしようと、アザゼルの部屋を訪れる主人公。\nすると彼女はぐっすりと眠っており……。","type":"harem-character","quest_ap":0}],"max_record_count":2}