{"data":[{"quest_id":3601,"title":"怒りに飲まれては","is_restricted":false,"is_r18":false,"harem_episode_info":{"episode_id":"3601_harem-character","heroine_is_aroused":true,"cleared_bonus_type":"none","is_story_of_encounter":true,"heroines":[{"heroine_type":"character","heroine_id":5082,"name":"不動明王[神化覚醒]"}],"condition_to_unlock":{"heroine_name":"不動明王[神化覚醒]","episode_title":"","level":1},"chapters":[{"a_chapter_id":"150820","chapter_id":"3601_harem-character","title":"第1話","is_cleared":true,"is_opened":true}]},"reward_info":{"reward_type":"item","item_id":1},"a_quest_id":"150820","is_new":false,"is_cleared":true,"is_opened":true,"has_area_boss":false,"description":"霊山の調査中、一行はテスタメントと遭遇し\n戦いになる。混戦の中で主人公が傷を負うと\n怒りにかられた不動明王が暴走してしまう。","type":"harem-character","quest_ap":0},{"quest_id":3602,"title":"ワタシはワタシ？","is_restricted":false,"is_r18":true,"harem_episode_info":{"episode_id":"3602_harem-character","heroine_is_aroused":true,"cleared_bonus_type":"acquire_ability","is_story_of_encounter":false,"heroines":[{"heroine_type":"character","heroine_id":5082,"name":"不動明王[神化覚醒]"}],"condition_to_unlock":{"heroine_name":"不動明王[神化覚醒]","episode_title":"怒りに飲まれては","level":35},"chapters":[{"a_chapter_id":"150821","chapter_id":"3602_harem-character","title":"第1話","is_cleared":false,"is_opened":true}]},"a_quest_id":"150821","is_new":true,"is_cleared":false,"is_opened":true,"has_area_boss":false,"description":"宿で主人公の部屋を訪ねる不動明王。\n過去の記憶を失っている彼女は、\n自分が何者かわからない不安を打ち明ける。","type":"harem-character","quest_ap":0}],"max_record_count":2}